[
  {
    "match_id": "2026-07-22_周三201",
    "competition": "K1联赛",
    "home_team": "首尔FC",
    "away_team": "浦项制铁",
    "home_win_prob": 0.5487,
    "draw_prob": 0.2266,
    "away_win_prob": 0.2247,
    "home_xg": 1.39,
    "away_xg": 1.29,
    "home_odds": 1.84,
    "draw_odds": 3.46,
    "away_odds": 4.53,
    "odds_synthetic": false,
    "handicap": null,
    "confidence": 0.1803,
    "wilson_trust": 0.3286,
    "model_raw": {
      "home": 0.5487,
      "draw": 0.2266,
      "away": 0.2247
    },
    "market_fair": null,
    "top_scores": [
      [
        1,
        1,
        0.1116
      ],
      [
        2,
        1,
        0.0957
      ],
      [
        1,
        0,
        0.0902
      ],
      [
        2,
        0,
        0.0777
      ],
      [
        1,
        2,
        0.0655
      ],
      [
        0,
        1,
        0.0653
      ],
      [
        2,
        2,
        0.0569
      ],
      [
        3,
        1,
        0.0546
      ]
    ],
    "total_goals": [
      [
        2,
        0.2282
      ],
      [
        3,
        0.2215
      ],
      [
        4,
        0.1632
      ],
      [
        1,
        0.1554
      ],
      [
        5,
        0.0985
      ],
      [
        0,
        0.0543
      ]
    ],
    "htft": {
      "HH": 0.2782,
      "HD": 0.0875,
      "HA": 0.0471,
      "DH": 0.2238,
      "DD": 0.0694,
      "DA": 0.0837,
      "AH": 0.0547,
      "AD": 0.0821,
      "AA": 0.0735
    },
    "htft_top3": [
      [
        "HH",
        0.2782
      ],
      [
        "DH",
        0.2238
      ],
      [
        "HD",
        0.0875
      ]
    ],
    "reverse_upset_risk": null,
    "reverse_direction": null,
    "reverse_compression": null,
    "same_odds_matched": 0,
    "same_odds_confidence": 0,
    "same_odds_bias": null,
    "combo_boost": 0.0,
    "djyy_enriched": false,
    "djyy_model_prob": null,
    "_djyy_id": null,
    "elo_home": 1534.1,
    "elo_away": 1500.0
  },
  {
    "match_id": "2026-07-22_周三202",
    "competition": "K1联赛",
    "home_team": "富川FC",
    "away_team": "安养FC",
    "home_win_prob": 0.3007,
    "draw_prob": 0.2536,
    "away_win_prob": 0.4457,
    "home_xg": 1.19,
    "away_xg": 1.3,
    "home_odds": 2.97,
    "draw_odds": 2.99,
    "away_odds": 2.65,
    "odds_synthetic": false,
    "handicap": null,
    "confidence": 0.1222,
    "wilson_trust": 0.2742,
    "model_raw": {
      "home": 0.3007,
      "draw": 0.2536,
      "away": 0.4457
    },
    "market_fair": null,
    "top_scores": [
      [
        1,
        1,
        0.1171
      ],
      [
        1,
        2,
        0.0901
      ],
      [
        0,
        1,
        0.0871
      ],
      [
        2,
        1,
        0.0763
      ],
      [
        1,
        0,
        0.0747
      ],
      [
        0,
        2,
        0.066
      ],
      [
        2,
        2,
        0.0592
      ],
      [
        0,
        0,
        0.0574
      ]
    ],
    "total_goals": [
      [
        2,
        0.234
      ],
      [
        3,
        0.224
      ],
      [
        1,
        0.1618
      ],
      [
        4,
        0.1611
      ],
      [
        5,
        0.0915
      ],
      [
        0,
        0.0574
      ]
    ],
    "htft": {
      "HH": 0.1099,
      "HD": 0.095,
      "HA": 0.0511,
      "DH": 0.1404,
      "DD": 0.0823,
      "DA": 0.1793,
      "AH": 0.0588,
      "AD": 0.0882,
      "AA": 0.1948
    },
    "htft_top3": [
      [
        "AA",
        0.1948
      ],
      [
        "DA",
        0.1793
      ],
      [
        "DH",
        0.1404
      ]
    ],
    "reverse_upset_risk": null,
    "reverse_direction": null,
    "reverse_compression": null,
    "same_odds_matched": 0,
    "same_odds_confidence": 0,
    "same_odds_bias": null,
    "combo_boost": 0.0,
    "djyy_enriched": false,
    "djyy_model_prob": null,
    "_djyy_id": null,
    "elo_home": 1465.9,
    "elo_away": 1497.0
  },
  {
    "match_id": "2026-07-22_周三203",
    "competition": "K1联赛",
    "home_team": "光州FC",
    "away_team": "金泉尚武",
    "home_win_prob": 0.3627,
    "draw_prob": 0.2535,
    "away_win_prob": 0.3838,
    "home_xg": 1.1,
    "away_xg": 1.28,
    "home_odds": 4.52,
    "draw_odds": 3.55,
    "away_odds": 1.82,
    "odds_synthetic": false,
    "handicap": null,
    "confidence": 0.1101,
    "wilson_trust": 0.2742,
    "model_raw": {
      "home": 0.4014,
      "draw": 0.2549,
      "away": 0.3437
    },
    "market_fair": null,
    "top_scores": [
      [
        0,
        1,
        0.132
      ],
      [
        1,
        1,
        0.1164
      ],
      [
        0,
        2,
        0.1066
      ],
      [
        1,
        2,
        0.09539999999999998
      ],
      [
        0,
        0,
        0.0828
      ],
      [
        1,
        0,
        0.071
      ],
      [
        0,
        3,
        0.056299999999999996
      ],
      [
        1,
        3,
        0.0538
      ],
      [
        2,
        1,
        0.0495
      ],
      [
        2,
        2,
        0.0432
      ]
    ],
    "total_goals": {
      "1.5": [
        0.2863,
        0.7137
      ],
      "2.5": [
        0.5426,
        0.45740000000000003
      ],
      "3.5": [
        0.7498,
        0.2502
      ],
      "4.5": [
        0.8622,
        0.1378
      ]
    },
    "htft": {
      "HH": 0.1672,
      "HD": 0.0973,
      "HA": 0.0524,
      "DH": 0.1798,
      "DD": 0.0828,
      "DA": 0.139,
      "AH": 0.0597,
      "AD": 0.0896,
      "AA": 0.1322
    },
    "htft_top3": [
      [
        "DH",
        0.1798
      ],
      [
        "HH",
        0.1672
      ],
      [
        "DA",
        0.139
      ]
    ],
    "reverse_upset_risk": null,
    "reverse_direction": null,
    "reverse_compression": null,
    "same_odds_matched": 0,
    "same_odds_confidence": 0,
    "same_odds_bias": null,
    "combo_boost": 0.0,
    "djyy_enriched": true,
    "djyy_model_prob": {
      "home": 0.1986,
      "draw": 0.2477,
      "away": 0.5532
    },
    "_djyy_id": 19648120,
    "elo_home": 1503.0,
    "elo_away": 1500.0
  },
  {
    "match_id": "2026-07-22_周三204",
    "competition": "挪超",
    "home_team": "博德闪耀",
    "away_team": "汉坎",
    "home_win_prob": 0.6998,
    "draw_prob": 0.1592,
    "away_win_prob": 0.1409,
    "home_xg": 2.68,
    "away_xg": 1.38,
    "home_odds": 1.1,
    "draw_odds": 11.47,
    "away_odds": 17.68,
    "odds_synthetic": false,
    "handicap": null,
    "confidence": 0.2669,
    "wilson_trust": 0.3876,
    "model_raw": {
      "home": 0.6886,
      "draw": 0.1593,
      "away": 0.1522
    },
    "market_fair": null,
    "top_scores": [
      [
        2,
        0,
        0.1139
      ],
      [
        1,
        0,
        0.1024
      ],
      [
        3,
        0,
        0.0897
      ],
      [
        2,
        1,
        0.08689999999999999
      ],
      [
        1,
        1,
        0.07139999999999999
      ],
      [
        3,
        1,
        0.0703
      ],
      [
        0,
        0,
        0.0444
      ],
      [
        2,
        2,
        0.0341
      ],
      [
        3,
        2,
        0.0327
      ],
      [
        0,
        1,
        0.0318
      ]
    ],
    "total_goals": {
      "1.5": [
        0.17850000000000002,
        0.8215
      ],
      "2.5": [
        0.3753,
        0.6247
      ],
      "3.5": [
        0.5751,
        0.425
      ],
      "4.5": [
        0.6881,
        0.3119
      ]
    },
    "htft": {
      "HH": 0.4268,
      "HD": 0.0664,
      "HA": 0.0358,
      "DH": 0.2177,
      "DD": 0.0449,
      "DA": 0.0369,
      "AH": 0.0498,
      "AD": 0.0747,
      "AA": 0.047
    },
    "htft_top3": [
      [
        "HH",
        0.4268
      ],
      [
        "DH",
        0.2177
      ],
      [
        "AD",
        0.0747
      ]
    ],
    "reverse_upset_risk": null,
    "reverse_direction": null,
    "reverse_compression": null,
    "same_odds_matched": 0,
    "same_odds_confidence": 0,
    "same_odds_bias": null,
    "combo_boost": 0.0,
    "djyy_enriched": true,
    "djyy_model_prob": {
      "home": 0.7476999999999999,
      "draw": 0.159,
      "away": 0.0933
    },
    "_djyy_id": 19629724,
    "elo_home": 1765.2,
    "elo_away": 1500.0
  },
  {
    "match_id": "2026-07-22_周三205",
    "competition": "挪超",
    "home_team": "利勒斯特",
    "away_team": "维京",
    "home_win_prob": 0.5451,
    "draw_prob": 0.2127,
    "away_win_prob": 0.2422,
    "home_xg": 1.41,
    "away_xg": 1.66,
    "home_odds": 3.21,
    "draw_odds": 3.7,
    "away_odds": 2.14,
    "odds_synthetic": false,
    "handicap": null,
    "confidence": 0.2336,
    "wilson_trust": 0.3876,
    "model_raw": {
      "home": 0.6028,
      "draw": 0.2092,
      "away": 0.188
    },
    "market_fair": null,
    "top_scores": [
      [
        1,
        1,
        0.1011
      ],
      [
        1,
        2,
        0.0929
      ],
      [
        0,
        1,
        0.0703
      ],
      [
        2,
        1,
        0.07
      ],
      [
        0,
        2,
        0.064
      ],
      [
        2,
        2,
        0.0639
      ],
      [
        1,
        0,
        0.057999999999999996
      ],
      [
        1,
        3,
        0.054900000000000004
      ],
      [
        0,
        0,
        0.0414
      ],
      [
        2,
        3,
        0.0414
      ]
    ],
    "total_goals": {
      "1.5": [
        0.1697,
        0.8303
      ],
      "2.5": [
        0.3728,
        0.6272
      ],
      "3.5": [
        0.596,
        0.40399999999999997
      ],
      "4.5": [
        0.7501000000000001,
        0.24989999999999998
      ]
    },
    "htft": {
      "HH": 0.3285,
      "HD": 0.0799,
      "HA": 0.043,
      "DH": 0.234,
      "DD": 0.0615,
      "DA": 0.0657,
      "AH": 0.0516,
      "AD": 0.0773,
      "AA": 0.0584
    },
    "htft_top3": [
      [
        "HH",
        0.3285
      ],
      [
        "DH",
        0.234
      ],
      [
        "HD",
        0.0799
      ]
    ],
    "reverse_upset_risk": null,
    "reverse_direction": null,
    "reverse_compression": null,
    "same_odds_matched": 0,
    "same_odds_confidence": 0,
    "same_odds_bias": null,
    "combo_boost": 0.0,
    "djyy_enriched": true,
    "djyy_model_prob": {
      "home": 0.3007,
      "draw": 0.22760000000000002,
      "away": 0.4717
    },
    "_djyy_id": 19629656,
    "elo_home": 1500.0,
    "elo_away": 1466.9
  },
  {
    "match_id": "2026-07-22_周三206",
    "competition": "美职联",
    "home_team": "迈阿密国际",
    "away_team": "芝加哥",
    "home_win_prob": 0.5794,
    "draw_prob": 0.1617,
    "away_win_prob": 0.2588,
    "home_xg": 4.034,
    "away_xg": 2.864,
    "home_odds": 1.5,
    "draw_odds": 5.38,
    "away_odds": 3.36,
    "odds_synthetic": true,
    "handicap": null,
    "confidence": 0.1956,
    "wilson_trust": 0.3286,
    "model_raw": {
      "home": 0.5952,
      "draw": 0.1439,
      "away": 0.2609
    },
    "market_fair": null,
    "top_scores": [
      [
        1,
        1,
        0.09849999999999999
      ],
      [
        2,
        1,
        0.0843
      ],
      [
        1,
        0,
        0.0842
      ],
      [
        2,
        0,
        0.0676
      ],
      [
        2,
        2,
        0.0623
      ],
      [
        0,
        1,
        0.0601
      ],
      [
        1,
        2,
        0.0565
      ],
      [
        3,
        1,
        0.0565
      ],
      [
        0,
        0,
        0.0557
      ],
      [
        3,
        2,
        0.0416
      ]
    ],
    "total_goals": {
      "1.5": [
        0.2,
        0.8
      ],
      "2.5": [
        0.401,
        0.599
      ],
      "3.5": [
        0.5921,
        0.40759999999999996
      ],
      "4.5": [
        0.737,
        0.263
      ]
    },
    "htft": {
      "HH": 0.3362,
      "HD": 0.1006,
      "HA": 0.0542,
      "DH": 0.1432,
      "DD": 0.0355,
      "DA": 0.0581,
      "AH": 0.0661,
      "AD": 0.0991,
      "AA": 0.1069
    },
    "htft_top3": [
      [
        "HH",
        0.3362
      ],
      [
        "DH",
        0.1432
      ],
      [
        "AA",
        0.1069
      ]
    ],
    "reverse_upset_risk": null,
    "reverse_direction": null,
    "reverse_compression": null,
    "same_odds_matched": 0,
    "same_odds_confidence": 0,
    "same_odds_bias": null,
    "combo_boost": 0.0,
    "djyy_enriched": true,
    "djyy_model_prob": {
      "home": 0.5127,
      "draw": 0.2372,
      "away": 0.2501
    },
    "_djyy_id": 19609611,
    "elo_home": 1500.0,
    "elo_away": 1500.0
  },
  {
    "match_id": "2026-07-22_周三207",
    "competition": "巴甲",
    "home_team": "沙佩科",
    "away_team": "弗拉门戈",
    "home_win_prob": 0.0626,
    "draw_prob": 0.1002,
    "away_win_prob": 0.8372,
    "home_xg": 0.457,
    "away_xg": 3.744,
    "home_odds": 13.91,
    "draw_odds": 8.68,
    "away_odds": 1.04,
    "odds_synthetic": true,
    "handicap": null,
    "confidence": 0.5539,
    "wilson_trust": 0.5975,
    "model_raw": {
      "home": 0.0159,
      "draw": 0.057,
      "away": 0.9271
    },
    "market_fair": null,
    "top_scores": [
      [
        1,
        1,
        0.1326
      ],
      [
        0,
        1,
        0.1263
      ],
      [
        0,
        0,
        0.0916
      ],
      [
        1,
        2,
        0.0892
      ],
      [
        0,
        2,
        0.0857
      ],
      [
        1,
        0,
        0.08410000000000001
      ],
      [
        2,
        1,
        0.0634
      ],
      [
        2,
        2,
        0.048600000000000004
      ],
      [
        2,
        0,
        0.042699999999999995
      ],
      [
        1,
        3,
        0.0403
      ]
    ],
    "total_goals": {
      "1.5": [
        0.302,
        0.698
      ],
      "2.5": [
        0.5631,
        0.43689999999999996
      ],
      "3.5": [
        0.7674,
        0.23260000000000003
      ],
      "4.5": [
        0.877,
        0.12300000000000001
      ]
    },
    "htft": {
      "HH": 0.0058,
      "HD": 0.0232,
      "HA": 0.0125,
      "DH": 0.0131,
      "DD": 0.0331,
      "DA": 0.1745,
      "AH": 0.059,
      "AD": 0.0885,
      "AA": 0.5902
    },
    "htft_top3": [
      [
        "AA",
        0.5902
      ],
      [
        "DA",
        0.1745
      ],
      [
        "AD",
        0.0885
      ]
    ],
    "reverse_upset_risk": null,
    "reverse_direction": null,
    "reverse_compression": null,
    "same_odds_matched": 0,
    "same_odds_confidence": 0,
    "same_odds_bias": null,
    "combo_boost": 0.0,
    "djyy_enriched": true,
    "djyy_model_prob": {
      "home": 0.2602,
      "draw": 0.2834,
      "away": 0.45640000000000003
    },
    "_djyy_id": 19621890,
    "elo_home": 1338.8,
    "elo_away": 1772.0
  },
  {
    "match_id": "2026-07-22_周三208",
    "competition": "巴甲",
    "home_team": "圣保罗",
    "away_team": "巴竞技",
    "home_win_prob": 0.2443,
    "draw_prob": 0.2701,
    "away_win_prob": 0.4856,
    "home_xg": 1.052,
    "away_xg": 1.586,
    "home_odds": 3.56,
    "draw_odds": 3.22,
    "away_odds": 1.79,
    "odds_synthetic": true,
    "handicap": null,
    "confidence": 0.1332,
    "wilson_trust": 0.2742,
    "model_raw": {
      "home": 0.2443,
      "draw": 0.2701,
      "away": 0.4856
    },
    "market_fair": null,
    "top_scores": [
      [
        0,
        1,
        0.1577
      ],
      [
        0,
        0,
        0.1387
      ],
      [
        1,
        1,
        0.1312
      ],
      [
        1,
        0,
        0.1152
      ],
      [
        0,
        2,
        0.0905
      ],
      [
        1,
        2,
        0.0769
      ],
      [
        2,
        1,
        0.0546
      ],
      [
        2,
        0,
        0.0473
      ]
    ],
    "total_goals": [
      [
        1,
        0.2729
      ],
      [
        2,
        0.2689
      ],
      [
        3,
        0.1787
      ],
      [
        0,
        0.1387
      ],
      [
        4,
        0.0881
      ],
      [
        5,
        0.0354
      ]
    ],
    "htft": {
      "HH": 0.0787,
      "HD": 0.0864,
      "HA": 0.0465,
      "DH": 0.1252,
      "DD": 0.0915,
      "DA": 0.212,
      "AH": 0.0551,
      "AD": 0.0827,
      "AA": 0.2219
    },
    "htft_top3": [
      [
        "AA",
        0.2219
      ],
      [
        "DA",
        0.212
      ],
      [
        "DH",
        0.1252
      ]
    ],
    "reverse_upset_risk": null,
    "reverse_direction": null,
    "reverse_compression": null,
    "same_odds_matched": 0,
    "same_odds_confidence": 0,
    "same_odds_bias": null,
    "combo_boost": 0.0,
    "djyy_enriched": false,
    "djyy_model_prob": null,
    "_djyy_id": null,
    "elo_home": 1557.9,
    "elo_away": 1604.1
  },
  {
    "match_id": "2026-07-22_周三209",
    "competition": "美职联",
    "home_team": "洛杉矶FC",
    "away_team": "盐湖城",
    "home_win_prob": 0.3466,
    "draw_prob": 0.2591,
    "away_win_prob": 0.3943,
    "home_xg": 1.182,
    "away_xg": 1.532,
    "home_odds": 2.51,
    "draw_odds": 3.36,
    "away_odds": 2.21,
    "odds_synthetic": true,
    "handicap": null,
    "confidence": 0.1219,
    "wilson_trust": 0.2742,
    "model_raw": {
      "home": 0.2882,
      "draw": 0.2673,
      "away": 0.4445
    },
    "market_fair": null,
    "top_scores": [
      [
        1,
        0,
        0.1272
      ],
      [
        2,
        0,
        0.11
      ],
      [
        1,
        1,
        0.1009
      ],
      [
        2,
        1,
        0.09939999999999999
      ],
      [
        0,
        0,
        0.0703
      ],
      [
        3,
        0,
        0.0658
      ],
      [
        3,
        1,
        0.0552
      ],
      [
        0,
        1,
        0.054299999999999994
      ],
      [
        1,
        2,
        0.046799999999999994
      ],
      [
        2,
        2,
        0.043
      ]
    ],
    "total_goals": {
      "1.5": [
        0.2519,
        0.7481
      ],
      "2.5": [
        0.4868,
        0.5132
      ],
      "3.5": [
        0.7082999999999999,
        0.2917
      ],
      "4.5": [
        0.8218000000000001,
        0.1782
      ]
    },
    "htft": {
      "HH": 0.0991,
      "HD": 0.0913,
      "HA": 0.0492,
      "DH": 0.1417,
      "DD": 0.0914,
      "DA": 0.1915,
      "AH": 0.0573,
      "AD": 0.086,
      "AA": 0.1925
    },
    "htft_top3": [
      [
        "AA",
        0.1925
      ],
      [
        "DA",
        0.1915
      ],
      [
        "DH",
        0.1417
      ]
    ],
    "reverse_upset_risk": null,
    "reverse_direction": null,
    "reverse_compression": null,
    "same_odds_matched": 0,
    "same_odds_confidence": 0,
    "same_odds_bias": null,
    "combo_boost": 0.0,
    "djyy_enriched": true,
    "djyy_model_prob": {
      "home": 0.5937,
      "draw": 0.2243,
      "away": 0.18170000000000003
    },
    "_djyy_id": 19609622,
    "elo_home": 1491.7,
    "elo_away": 1500.0
  },
  {
    "match_id": "2026-07-22_周三210",
    "competition": "欧冠",
    "home_team": "奥莫尼亚",
    "away_team": "阿拉木图",
    "home_win_prob": 0.1915,
    "draw_prob": 0.2451,
    "away_win_prob": 0.5634,
    "home_xg": 0.94,
    "away_xg": 1.775,
    "home_odds": 4.54,
    "draw_odds": 3.55,
    "away_odds": 1.54,
    "odds_synthetic": true,
    "handicap": null,
    "confidence": 0.1851,
    "wilson_trust": 0.3286,
    "model_raw": {
      "home": 0.1915,
      "draw": 0.2451,
      "away": 0.5634
    },
    "market_fair": null,
    "top_scores": [
      [
        0,
        1,
        0.123
      ],
      [
        1,
        1,
        0.1137
      ],
      [
        0,
        2,
        0.1082
      ],
      [
        1,
        2,
        0.0965
      ],
      [
        0,
        0,
        0.0715
      ],
      [
        1,
        0,
        0.0674
      ],
      [
        0,
        3,
        0.0618
      ],
      [
        1,
        3,
        0.0571
      ]
    ],
    "total_goals": [
      [
        2,
        0.2514
      ],
      [
        3,
        0.2191
      ],
      [
        1,
        0.1904
      ],
      [
        4,
        0.1432
      ],
      [
        5,
        0.0739
      ],
      [
        0,
        0.0715
      ]
    ],
    "htft": {
      "HH": 0.0567,
      "HD": 0.0791,
      "HA": 0.0426,
      "DH": 0.0986,
      "DD": 0.0821,
      "DA": 0.2341,
      "AH": 0.0505,
      "AD": 0.0758,
      "AA": 0.2804
    },
    "htft_top3": [
      [
        "AA",
        0.2804
      ],
      [
        "DA",
        0.2341
      ],
      [
        "DH",
        0.0986
      ]
    ],
    "reverse_upset_risk": null,
    "reverse_direction": null,
    "reverse_compression": null,
    "same_odds_matched": 0,
    "same_odds_confidence": 0,
    "same_odds_bias": null,
    "combo_boost": 0.0,
    "djyy_enriched": false,
    "djyy_model_prob": null,
    "_djyy_id": null,
    "elo_home": 1381.3,
    "elo_away": 1499.3
  },
  {
    "match_id": "2026-07-22_周四202",
    "competition": "巴甲",
    "home_team": "博塔弗戈",
    "away_team": "维多利亚",
    "home_win_prob": 0.5382,
    "draw_prob": 0.2297,
    "away_win_prob": 0.2321,
    "home_xg": 1.966,
    "away_xg": 1.235,
    "home_odds": 1.62,
    "draw_odds": 3.79,
    "away_odds": 3.75,
    "odds_synthetic": true,
    "handicap": null,
    "confidence": 0.1768,
    "wilson_trust": 0.3286,
    "model_raw": {
      "home": 0.5381,
      "draw": 0.2297,
      "away": 0.2321
    },
    "market_fair": null,
    "top_scores": [
      [
        1,
        1,
        0.1061
      ],
      [
        2,
        1,
        0.0967
      ],
      [
        1,
        0,
        0.0908
      ],
      [
        2,
        0,
        0.0807
      ],
      [
        1,
        2,
        0.0668
      ],
      [
        0,
        1,
        0.0606
      ],
      [
        2,
        2,
        0.0602
      ],
      [
        3,
        1,
        0.0568
      ]
    ],
    "total_goals": [
      [
        3,
        0.2268
      ],
      [
        2,
        0.2233
      ],
      [
        4,
        0.1687
      ],
      [
        1,
        0.1515
      ],
      [
        5,
        0.0979
      ],
      [
        0,
        0.0505
      ]
    ],
    "htft": {
      "HH": 0.2681,
      "HD": 0.089,
      "HA": 0.0479,
      "DH": 0.2207,
      "DD": 0.0707,
      "DA": 0.0877,
      "AH": 0.0554,
      "AD": 0.0831,
      "AA": 0.0774
    },
    "htft_top3": [
      [
        "HH",
        0.2681
      ],
      [
        "DH",
        0.2207
      ],
      [
        "HD",
        0.089
      ]
    ],
    "reverse_upset_risk": null,
    "reverse_direction": null,
    "reverse_compression": null,
    "same_odds_matched": 0,
    "same_odds_confidence": 0,
    "same_odds_bias": null,
    "combo_boost": 0.0,
    "djyy_enriched": false,
    "djyy_model_prob": null,
    "_djyy_id": null,
    "elo_home": 1639.0,
    "elo_away": 1603.0
  }
]