{
  "stable": [],
  "value": [
    {
      "match": "2026-07-23_周四205",
      "sel": "away",
      "odds": 3.5,
      "stake": 800.0
    }
  ],
  "lottery": [
    {
      "match": "2026-07-23_周四207",
      "sel": "away",
      "odds": 3.7,
      "stake": 615.39
    },
    {
      "match": "2026-07-23_周四206",
      "sel": "away",
      "odds": 6.05,
      "stake": 284.61
    }
  ],
  "total_stake": 1700.0,
  "expected_roi": 0.4388,
  "bankroll": 10000,
  "breaker_multiplier": 0.8999999999999999
}